deadline/blender_adaptor/__init__.py
deadline/blender_adaptor/_version.py
deadline/blender_adaptor/BlenderAdaptor/BlenderAdaptor.json
deadline/blender_adaptor/BlenderAdaptor/__init__.py
deadline/blender_adaptor/BlenderAdaptor/__main__.py
deadline/blender_adaptor/BlenderAdaptor/_cli.py
deadline/blender_adaptor/BlenderAdaptor/adaptor.py
deadline/blender_adaptor/BlenderAdaptor/py.typed
deadline/blender_adaptor/BlenderAdaptor/schemas/init_data.schema.json
deadline/blender_adaptor/BlenderAdaptor/schemas/run_data.schema.json
deadline/blender_adaptor/BlenderClient/__init__.py
deadline/blender_adaptor/BlenderClient/blender_client.py
deadline/blender_adaptor/BlenderClient/py.typed
deadline/blender_adaptor/BlenderClient/render_handlers/__init__.py
deadline/blender_adaptor/BlenderClient/render_handlers/cycles_blender_handler.py
deadline/blender_adaptor/BlenderClient/render_handlers/default_blender_handler.py
deadline/blender_adaptor/BlenderClient/render_handlers/workbench_blender_handler.py
deadline/blender_submitter/_version.py
deadline/blender_submitter/addons/deadline_cloud_blender_submitter/__init__.py
deadline/blender_submitter/addons/deadline_cloud_blender_submitter/_version.py
deadline/blender_submitter/addons/deadline_cloud_blender_submitter/adaptor_override_environment.yaml
deadline/blender_submitter/addons/deadline_cloud_blender_submitter/addonpreferences.py
deadline/blender_submitter/addons/deadline_cloud_blender_submitter/blender_utils.py
deadline/blender_submitter/addons/deadline_cloud_blender_submitter/default_blender_template.yaml
deadline/blender_submitter/addons/deadline_cloud_blender_submitter/logutil.py
deadline/blender_submitter/addons/deadline_cloud_blender_submitter/ocio_utils.py
deadline/blender_submitter/addons/deadline_cloud_blender_submitter/open_deadline_cloud_dialog.py
deadline/blender_submitter/addons/deadline_cloud_blender_submitter/sanity_checks.py
deadline/blender_submitter/addons/deadline_cloud_blender_submitter/scene_settings_widget.py
deadline_cloud_for_blender-0.5.5.dist-info/METADATA
deadline_cloud_for_blender-0.5.5.dist-info/WHEEL
deadline_cloud_for_blender-0.5.5.dist-info/entry_points.txt
deadline_cloud_for_blender-0.5.5.dist-info/licenses/LICENSE
deadline_cloud_for_blender-0.5.5.dist-info/licenses/NOTICE
deadline_cloud_for_blender-0.5.5.dist-info/RECORD
